[
  {
    "id": 1,
    "name": "Kylian Mbappé",
    "facts": { "age": 25, "country": 18, "position": "ST", "club": 73 },
    "image": 1,
    "rating": 91,
    "attributes": {
      "stat1": 97,
      "stat2": 36,
      "stat3": 92,
      "stat4": 80,
      "stat5": 78,
      "stat6": 90
    }
  },
  {
    "id": 3,
    "name": "Erling Haaland",
    "facts": { "age": 24, "country": 36, "position": "ST", "club": 10 },
    "image": 3,
    "rating": 91,
    "attributes": {
      "stat1": 89,
      "stat2": 45,
      "stat3": 80,
      "stat4": 66,
      "stat5": 88,
      "stat6": 93
    }
  },
  {
    "id": 4,
    "name": "Kevin De Bruyne",
    "facts": { "age": 33, "country": 7, "position": "CM", "club": 10 },
    "image": 4,
    "rating": 91,
    "attributes": {
      "stat1": 72,
      "stat2": 65,
      "stat3": 87,
      "stat4": 94,
      "stat5": 78,
      "stat6": 88
    }
  },
  {
    "id": 6,
    "name": "Lionel Messi",
    "facts": { "age": 37, "country": 52, "position": "CF", "club": 112893 },
    "image": 6,
    "rating": 90,
    "attributes": {
      "stat1": 80,
      "stat2": 33,
      "stat3": 94,
      "stat4": 90,
      "stat5": 64,
      "stat6": 87
    }
  },
  {
    "id": 8,
    "name": "Karim Benzema",
    "facts": { "age": 36, "country": 18, "position": "CF", "club": 607 },
    "image": 8,
    "rating": 90,
    "attributes": {
      "stat1": 79,
      "stat2": 39,
      "stat3": 87,
      "stat4": 83,
      "stat5": 78,
      "stat6": 88
    }
  },
  {
    "id": 9,
    "name": "Thibaut Courtois",
    "facts": { "age": 32, "country": 7, "position": "GK", "club": 243 },
    "image": 9,
    "rating": 90,
    "attributes": {
      "stat1": 85,
      "stat2": 46,
      "stat3": 93,
      "stat4": 76,
      "stat5": 90,
      "stat6": 89
    }
  },
  {
    "id": 10,
    "name": "Harry Kane",
    "facts": { "age": 31, "country": 14, "position": "ST", "club": 21 },
    "image": 10,
    "rating": 90,
    "attributes": {
      "stat1": 69,
      "stat2": 49,
      "stat3": 83,
      "stat4": 84,
      "stat5": 83,
      "stat6": 93
    }
  },
  {
    "id": 12,
    "name": "Robert Lewandowski",
    "facts": { "age": 35, "country": 37, "position": "ST", "club": 241 },
    "image": 12,
    "rating": 90,
    "attributes": {
      "stat1": 75,
      "stat2": 44,
      "stat3": 87,
      "stat4": 80,
      "stat5": 84,
      "stat6": 91
    }
  },
  {
    "id": 13,
    "name": "Mohamed Salah",
    "facts": { "age": 32, "country": 111, "position": "RW", "club": 9 },
    "image": 13,
    "rating": 89,
    "attributes": {
      "stat1": 89,
      "stat2": 45,
      "stat3": 88,
      "stat4": 81,
      "stat5": 76,
      "stat6": 87
    }
  },
  {
    "id": 16,
    "name": "Rúben Dias",
    "facts": { "age": 27, "country": 38, "position": "CB", "club": 10 },
    "image": 16,
    "rating": 89,
    "attributes": {
      "stat1": 62,
      "stat2": 89,
      "stat3": 69,
      "stat4": 66,
      "stat5": 87,
      "stat6": 39
    }
  },
  {
    "id": 17,
    "name": "Vinícius Júnior",
    "facts": { "age": 24, "country": 54, "position": "LW", "club": 243 },
    "image": 17,
    "rating": 89,
    "attributes": {
      "stat1": 95,
      "stat2": 29,
      "stat3": 90,
      "stat4": 78,
      "stat5": 68,
      "stat6": 82
    }
  },
  {
    "id": 18,
    "name": "Rodri",
    "facts": { "age": 28, "country": 45, "position": "CDM", "club": 10 },
    "image": 18,
    "rating": 89,
    "attributes": {
      "stat1": 58,
      "stat2": 85,
      "stat3": 80,
      "stat4": 80,
      "stat5": 84,
      "stat6": 73
    }
  },
  {
    "id": 19,
    "name": "Neymar Jr",
    "facts": { "age": 32, "country": 54, "position": "LW", "club": 605 },
    "image": 19,
    "rating": 89,
    "attributes": {
      "stat1": 86,
      "stat2": 37,
      "stat3": 93,
      "stat4": 85,
      "stat5": 61,
      "stat6": 83
    }
  },
  {
    "id": 21,
    "name": "ter Stegen",
    "facts": { "age": 32, "country": 21, "position": "GK", "club": 241 },
    "image": 21,
    "rating": 89,
    "attributes": {
      "stat1": 86,
      "stat2": 47,
      "stat3": 91,
      "stat4": 89,
      "stat5": 86,
      "stat6": 85
    }
  },
  {
    "id": 22,
    "name": "Virgil van Dijk",
    "facts": { "age": 33, "country": 34, "position": "CB", "club": 9 },
    "image": 22,
    "rating": 89,
    "attributes": {
      "stat1": 78,
      "stat2": 89,
      "stat3": 72,
      "stat4": 71,
      "stat5": 86,
      "stat6": 60
    }
  },
  {
    "id": 23,
    "name": "Alisson",
    "facts": { "age": 31, "country": 54, "position": "GK", "club": 9 },
    "image": 23,
    "rating": 89,
    "attributes": {
      "stat1": 86,
      "stat2": 56,
      "stat3": 89,
      "stat4": 85,
      "stat5": 90,
      "stat6": 85
    }
  },
  {
    "id": 25,
    "name": "Casemiro",
    "facts": { "age": 32, "country": 54, "position": "CDM", "club": 11 },
    "image": 25,
    "rating": 89,
    "attributes": {
      "stat1": 63,
      "stat2": 89,
      "stat3": 73,
      "stat4": 79,
      "stat5": 88,
      "stat6": 75
    }
  },
  {
    "id": 27,
    "name": "Bruno Fernandes",
    "facts": { "age": 29, "country": 38, "position": "CAM", "club": 11 },
    "image": 27,
    "rating": 88,
    "attributes": {
      "stat1": 71,
      "stat2": 69,
      "stat3": 83,
      "stat4": 90,
      "stat5": 77,
      "stat6": 86
    }
  },
  {
    "id": 29,
    "name": "Antoine Griezmann",
    "facts": { "age": 33, "country": 18, "position": "ST", "club": 240 },
    "image": 29,
    "rating": 88,
    "attributes": {
      "stat1": 80,
      "stat2": 58,
      "stat3": 88,
      "stat4": 87,
      "stat5": 75,
      "stat6": 88
    }
  },
  {
    "id": 30,
    "name": "Victor Osimhen",
    "facts": { "age": 25, "country": 133, "position": "ST", "club": 116365 },
    "image": 30,
    "rating": 88,
    "attributes": {
      "stat1": 90,
      "stat2": 42,
      "stat3": 83,
      "stat4": 66,
      "stat5": 82,
      "stat6": 86
    }
  }
]
